nso_api/__init__.py
nso_api/imink.py
nso_api/jwt.py
nso_api/nso_api.py
nso_api/nso_api_account.py
nso_api/nso_api_acnh.py
nso_api/nso_api_s2.py
nso_api/nso_api_s3.py
nso_api/nso_expiring_token.py
nso_api/utils.py
nso_api-0.9.2.dist-info/METADATA
nso_api-0.9.2.dist-info/WHEEL
nso_api-0.9.2.dist-info/licenses/LICENSE
nso_api-0.9.2.dist-info/RECORD
