Metadata-Version: 2.1
Name: nso-api
Version: 0.9.2
Project-URL: Homepage, https://github.com/Jetsurf/nso-api
Project-URL: Bug Tracker, https://github.com/Jetsurf/nso-api/issues
License-File: LICENSE
Classifier: License :: OSI Approved :: GNU General Public License v3 (GPLv3)
Classifier: Operating System :: OS Independent
Classifier: Programming Language :: Python :: 3
Requires-Python: >=3.6
